kfx/__init__.py
kfx/dsl/__init__.py
kfx/dsl/_artifact_location.py
kfx/dsl/_compat.py
kfx/dsl/_transformers.py
kfx/vis/__init__.py
kfx/vis/_helpers.py
kfx/vis/enums.py
kfx/vis/models.py
kfx/vis/vega.py
kfx-0.1.0.dist-info/WHEEL
kfx-0.1.0.dist-info/METADATA
kfx-0.1.0.dist-info/RECORD
