Metadata-Version: 2.1
Name: kfx
Version: 0.1.0
Summary: Extensions for kubeflow pipeline sdk.
Home-page: https://github.com/e2fyi/kfx
License: Apache-2.0
Keywords: kfx,kubeflow,pipelines,contrib,sdk
Author: eterna2
Author-email: eterna2@hotmail.com
Maintainer: eterna2
Maintainer-email: eterna2@hotmail.com
Requires-Python: >=3.6,<4
Classifier: Development Status :: 2 - Pre-Alpha
Classifier: Intended Audience :: Developers
Classifier: License :: OSI Approved :: Apache Software License
Classifier: Natural Language :: English
Classifier: Programming Language :: Python :: 3
Classifier: Programming Language :: Python :: 3.6
Classifier: Programming Language :: Python :: 3.7
Classifier: Programming Language :: Python :: 3.8
Classifier: Programming Language :: Python :: 3.9
Requires-Dist: kfp (>=0.2.0,<2)
Requires-Dist: pydantic (>=1.0.0,<2.0.0)
Requires-Dist: typing-extensions
Project-URL: Changelog, https://github.com/e2fyi/kfx/blob/master/CHANGELOG.md
Project-URL: Documentation, https://kfx.readthedocs.io/en/latest/
Project-URL: Repository, https://github.com/e2fyi/kfx
